ai_locators/__init__.py
ai_locators/selector.py
ai_locators-0.1.1.dist-info/METADATA
ai_locators-0.1.1.dist-info/WHEEL
ai_locators-0.1.1.dist-info/RECORD
