Metadata-Version: 2.4
Name: ai-locators
Version: 0.1.1
Summary: AI-powered locators for Playwright
Author-email: Surfing Devs <surfing.devs@gmail.com>, Lila <info@lila.dev>
License-Expression: MIT
Requires-Python: >=3.10
Requires-Dist: loguru~=0.7
Requires-Dist: openai~=1.0
Requires-Dist: playwright~=1.40
Provides-Extra: dev
Requires-Dist: pytest-playwright~=0.7; extra == 'dev'
Requires-Dist: pytest>=8.0; extra == 'dev'
